[
  {
    "UniprotName_A":"A0A087WX54",
    "UniprotName_B":"THAP1"
  },
  {
    "UniprotName_A":"A0A087WX54",
    "UniprotName_B":"PSA3"
  },
  {
    "UniprotName_A":"A0A087X2D5",
    "UniprotName_B":"RM47"
  },
  {
    "UniprotName_A":"TM129",
    "UniprotName_B":"DERL1"
  },
  {
    "UniprotName_A":"TM129",
    "UniprotName_B":"1A03"
  },
  {
    "UniprotName_A":"UBA6",
    "UniprotName_B":"UB2D2"
  },
  {
    "UniprotName_A":"UBA6",
    "UniprotName_B":"UBC"
  },
  {
    "UniprotName_A":"UBA6",
    "UniprotName_B":"UBD"
  },
  {
    "UniprotName_A":"UBA6",
    "UniprotName_B":"UBE2Z"
  },
  {
    "UniprotName_A":"UBA6",
    "UniprotName_B":"UCHL3"
  },
  {
    "UniprotName_A":"UBA6",
    "UniprotName_B":"VIGLN"
  },
  {
    "UniprotName_A":"UBA6",
    "UniprotName_B":"UBP48"
  },
  {
    "UniprotName_A":"UBA6",
    "UniprotName_B":"PYRG1"
  },
  {
    "UniprotName_A":"UBA6",
    "UniprotName_B":"UB2L3"
  },
  {
    "UniprotName_A":"ESYT2",
    "UniprotName_B":"ESYT1"
  },
  {
    "UniprotName_A":"MED19",
    "UniprotName_B":"RPAB5"
  },
  {
    "UniprotName_A":"MED19",
    "UniprotName_B":"RPAP2"
  },
  {
    "UniprotName_A":"MED19",
    "UniprotName_B":"AFF4"
  },
  {
    "UniprotName_A":"MED19",
    "UniprotName_B":"ELL2"
  },
  {
    "UniprotName_A":"MED19",
    "UniprotName_B":"CCNC"
  },
  {
    "UniprotName_A":"MED19",
    "UniprotName_B":"RPB9"
  },
  {
    "UniprotName_A":"MED19",
    "UniprotName_B":"RPAB3"
  },
  {
    "UniprotName_A":"MED19",
    "UniprotName_B":"RPAB1"
  },
  {
    "UniprotName_A":"MED19",
    "UniprotName_B":"RPAB2"
  },
  {
    "UniprotName_A":"MED19",
    "UniprotName_B":"MED26"
  },
  {
    "UniprotName_A":"MED19",
    "UniprotName_B":"RPB11"
  },
  {
    "UniprotName_A":"MED19",
    "UniprotName_B":"RPB7"
  },
  {
    "UniprotName_A":"MED19",
    "UniprotName_B":"RPB4"
  },
  {
    "UniprotName_A":"MED19",
    "UniprotName_B":"RPB3"
  },
  {
    "UniprotName_A":"MED19",
    "UniprotName_B":"RPB2"
  },
  {
    "UniprotName_A":"MED19",
    "UniprotName_B":"RPB1"
  },
  {
    "UniprotName_A":"MED19",
    "UniprotName_B":"MED10"
  },
  {
    "UniprotName_A":"MED19",
    "UniprotName_B":"MED31"
  },
  {
    "UniprotName_A":"MED19",
    "UniprotName_B":"MED11"
  },
  {
    "UniprotName_A":"MED19",
    "UniprotName_B":"MED22"
  },
  {
    "UniprotName_A":"MED19",
    "UniprotName_B":"MED21"
  },
  {
    "UniprotName_A":"MED19",
    "UniprotName_B":"MED28"
  },
  {
    "UniprotName_A":"MED19",
    "UniprotName_B":"MED30"
  },
  {
    "UniprotName_A":"MED19",
    "UniprotName_B":"MED9"
  },
  {
    "UniprotName_A":"MED19",
    "UniprotName_B":"MED20"
  },
  {
    "UniprotName_A":"MED19",
    "UniprotName_B":"MED18"
  },
  {
    "UniprotName_A":"MED19",
    "UniprotName_B":"MED8"
  },
  {
    "UniprotName_A":"MED19",
    "UniprotName_B":"MED7"
  },
  {
    "UniprotName_A":"MED19",
    "UniprotName_B":"MED6"
  },
  {
    "UniprotName_A":"MED19",
    "UniprotName_B":"MED19"
  },
  {
    "UniprotName_A":"MED19",
    "UniprotName_B":"MED4"
  },
  {
    "UniprotName_A":"MED19",
    "UniprotName_B":"MED27"
  },
  {
    "UniprotName_A":"MED19",
    "UniprotName_B":"CDK19"
  },
  {
    "UniprotName_A":"MED19",
    "UniprotName_B":"CDK8"
  },
  {
    "UniprotName_A":"MED19",
    "UniprotName_B":"MED17"
  },
  {
    "UniprotName_A":"MED19",
    "UniprotName_B":"MED25"
  },
  {
    "UniprotName_A":"MED19",
    "UniprotName_B":"MED16"
  },
  {
    "UniprotName_A":"MED19",
    "UniprotName_B":"MED24"
  },
  {
    "UniprotName_A":"MED19",
    "UniprotName_B":"MED15"
  },
  {
    "UniprotName_A":"MED19",
    "UniprotName_B":"MED23"
  },
  {
    "UniprotName_A":"MED19",
    "UniprotName_B":"MED14"
  },
  {
    "UniprotName_A":"MED19",
    "UniprotName_B":"MED1"
  },
  {
    "UniprotName_A":"MED19",
    "UniprotName_B":"MED12"
  },
  {
    "UniprotName_A":"MED19",
    "UniprotName_B":"MED13"
  },
  {
    "UniprotName_A":"MED19",
    "UniprotName_B":"MD13L"
  },
  {
    "UniprotName_A":"SHOT1",
    "UniprotName_B":"MEG10"
  },
  {
    "UniprotName_A":"RHG10",
    "UniprotName_B":"3BP2"
  },
  {
    "UniprotName_A":"RHG10",
    "UniprotName_B":"ANS1A"
  },
  {
    "UniprotName_A":"A2IXV5",
    "UniprotName_B":"PTN6"
  },
  {
    "UniprotName_A":"NBAS",
    "UniprotName_B":"STX18"
  },
  {
    "UniprotName_A":"MBPHL",
    "UniprotName_B":"TNS2"
  },
  {
    "UniprotName_A":"VWA8",
    "UniprotName_B":"MEG10"
  },
  {
    "UniprotName_A":"VP37C",
    "UniprotName_B":"TS101"
  },
  {
    "UniprotName_A":"VP37C",
    "UniprotName_B":"VPS28"
  },
  {
    "UniprotName_A":"TM189",
    "UniprotName_B":"UBE2N"
  },
  {
    "UniprotName_A":"TPC13",
    "UniprotName_B":"TPPC3"
  },
  {
    "UniprotName_A":"CNOT1",
    "UniprotName_B":"CNOT2"
  },
  {
    "UniprotName_A":"CNOT1",
    "UniprotName_B":"CNOT8"
  },
  {
    "UniprotName_A":"CNOT1",
    "UniprotName_B":"TNR6C"
  },
  {
    "UniprotName_A":"CNOT1",
    "UniprotName_B":"CNOT6"
  },
  {
    "UniprotName_A":"CNOT1",
    "UniprotName_B":"CNOT7"
  },
  {
    "UniprotName_A":"CNOT1",
    "UniprotName_B":"CNO6L"
  },
  {
    "UniprotName_A":"CNOT1",
    "UniprotName_B":"RN219"
  },
  {
    "UniprotName_A":"CNOT1",
    "UniprotName_B":"RCD1"
  },
  {
    "UniprotName_A":"CNOT1",
    "UniprotName_B":"TOB1"
  },
  {
    "UniprotName_A":"CNOT1",
    "UniprotName_B":"CNO10"
  },
  {
    "UniprotName_A":"CNOT1",
    "UniprotName_B":"CAZA2"
  },
  {
    "UniprotName_A":"CNOT1",
    "UniprotName_B":"CNOT3"
  },
  {
    "UniprotName_A":"CNOT1",
    "UniprotName_B":"CNOT4"
  },
  {
    "UniprotName_A":"IGIP",
    "UniprotName_B":"JIP2"
  },
  {
    "UniprotName_A":"MYH7B",
    "UniprotName_B":"TNS2"
  },
  {
    "UniprotName_A":"RHG32",
    "UniprotName_B":"MEG10"
  },
  {
    "UniprotName_A":"RHG32",
    "UniprotName_B":"RHOA"
  },
  {
    "UniprotName_A":"RHG32",
    "UniprotName_B":"RAC1"
  },
  {
    "UniprotName_A":"WASH1",
    "UniprotName_B":"BECN1"
  },
  {
    "UniprotName_A":"SFI1",
    "UniprotName_B":"CETN2"
  },
  {
    "UniprotName_A":"PP2D1",
    "UniprotName_B":"A4"
  },
  {
    "UniprotName_A":"CENPX",
    "UniprotName_B":"FANCL"
  },
  {
    "UniprotName_A":"CENPX",
    "UniprotName_B":"FANCA"
  },
  {
    "UniprotName_A":"MI4GD",
    "UniprotName_B":"DD19A"
  },
  {
    "UniprotName_A":"C1T9B",
    "UniprotName_B":"C1T9A"
  },
  {
    "UniprotName_A":"EIFCL",
    "UniprotName_B":"EIF3A"
  },
  {
    "UniprotName_A":"EIFCL",
    "UniprotName_B":"EIF3E"
  },
  {
    "UniprotName_A":"MCIN",
    "UniprotName_B":"GEMI"
  },
  {
    "UniprotName_A":"VFLIP_HHV8P",
    "UniprotName_B":"TRAF2"
  },
  {
    "UniprotName_A":"VFLIP_HHV8P",
    "UniprotName_B":"NEMO"
  },
  {
    "UniprotName_A":"VIRF1_HHV8P",
    "UniprotName_B":"CBP"
  },
  {
    "UniprotName_A":"VIRF1_HHV8P",
    "UniprotName_B":"EP300"
  },
  {
    "UniprotName_A":"APRIO",
    "UniprotName_B":"GRP78"
  },
  {
    "UniprotName_A":"UBXN8",
    "UniprotName_B":"TERA"
  }
]